LICENSE
MANIFEST.in
README.md
setup.py
fracfocustools/__init__.py
fracfocustools/core.py
fracfocustools/helpers1.py
fracfocustools/helpers2.py
fracfocustools.egg-info/PKG-INFO
fracfocustools.egg-info/SOURCES.txt
fracfocustools.egg-info/dependency_links.txt
fracfocustools.egg-info/requires.txt
fracfocustools.egg-info/top_level.txt