Metadata-Version: 1.0
Name: fracfocustools
Version: 0.0.5
Summary: Tools for maipulating data acquired from fracfous.org
Home-page: https://github.com/SkyTruth/fracfocustools
Author: Paul Woods, SkyTruth
Author-email: paul@skytruth.org
License: Copyright (c) 2012, SkyTruth
